{
  "actions": [
    {
      "acted_at": "2017-06-07", 
      "action_code": "Intro-H", 
      "references": [], 
      "text": "Introduced in House", 
      "type": "action"
    }, 
    {
      "acted_at": "2017-06-07", 
      "action_code": "H11100", 
      "committees": [
        "HSII"
      ], 
      "references": [], 
      "status": "REFERRED", 
      "text": "Referred to the House Committee on Natural Resources.", 
      "type": "referral"
    }, 
    {
      "acted_at": "2017-06-16", 
      "action_code": "", 
      "committees": [
        "HSII"
      ], 
      "references": [], 
      "text": "Referred to the Subcommittee on Water, Power and Oceans.", 
      "type": "referral"
    }
  ], 
  "amendments": [], 
  "bill_id": "hr2799-115", 
  "bill_type": "hr", 
  "by_request": false, 
  "committee_reports": [], 
  "committees": [
    {
      "activity": [
        "referral"
      ], 
      "committee": "House Natural Resources", 
      "committee_id": "HSII"
    }, 
    {
      "activity": [
        "referral"
      ], 
      "committee": "House Natural Resources", 
      "committee_id": "HSII", 
      "subcommittee": "Subcommittee on Water, Power and Oceans", 
      "subcommittee_id": "13"
    }
  ], 
  "congress": "115", 
  "cosponsors": [
    {
      "bioguide_id": "G000559", 
      "district": "3", 
      "name": "Garamendi, John", 
      "original_cosponsor": true, 
      "sponsored_at": "2017-06-07", 
      "state": "CA", 
      "title": "Rep", 
      "withdrawn_at": null
    }, 
    {
      "bioguide_id": "H001068", 
      "district": "2", 
      "name": "Huffman, Jared", 
      "original_cosponsor": true, 
      "sponsored_at": "2017-06-07", 
      "state": "CA", 
      "title": "Rep", 
      "withdrawn_at": null
    }, 
    {
      "bioguide_id": "S001175", 
      "district": "14", 
      "name": "Speier, Jackie", 
      "original_cosponsor": true, 
      "sponsored_at": "2017-06-07", 
      "state": "CA", 
      "title": "Rep", 
      "withdrawn_at": null
    }, 
    {
      "bioguide_id": "S001193", 
      "district": "15", 
      "name": "Swalwell, Eric", 
      "original_cosponsor": true, 
      "sponsored_at": "2017-06-07", 
      "state": "CA", 
      "title": "Rep", 
      "withdrawn_at": null
    }
  ], 
  "enacted_as": null, 
  "history": {
    "active": false, 
    "awaiting_signature": false, 
    "enacted": false, 
    "vetoed": false
  }, 
  "introduced_at": "2017-06-07", 
  "number": "2799", 
  "official_title": "To amend the Reclamation Wastewater and Groundwater Study and Facilities Act to authorize certain recycled water projects, and for other purposes.", 
  "popular_title": null, 
  "related_bills": [], 
  "short_title": "Western Water Recycling and Drought Relief Act", 
  "sponsor": {
    "bioguide_id": "M001166", 
    "district": "9", 
    "name": "McNerney, Jerry", 
    "state": "CA", 
    "title": "Rep", 
    "type": "person"
  }, 
  "status": "REFERRED", 
  "status_at": "2017-06-07", 
  "subjects": [
    "Water resources development"
  ], 
  "subjects_top_term": "Water resources development", 
  "summary": {
    "as": "Introduced in House", 
    "date": "2017-06-07T04:00:00Z", 
    "text": "Western Water Recycling and Drought Relief Act\n\nThis bill amends the Reclamation Wastewater and Groundwater Study and Facilities Act to authorize the Department of the Interior to participate in the design, planning, and construction of recycled water system facilities in California in cooperation with:\n\n the cities of Benicia, Brentwood, Redwood City, Pleasanton, Hayward, Mountain View, Palo Alto, Sunnyvale, and Turlock; the Dublin San Ramon Services District and the Dublin San Ramon Services District/East Bay Municipal Utility District Recycled Water Authority; the Santa Clara Valley Water District; the Central Contra Costa Sanitary District; the Delta Diablo; the Ironhouse Sanitary District; the Monterey Regional Water Pollution Control Agency; the San Jose Water Company; and the West Bay Sanitary District. The bill also authorizes Interior to participate in the design, planning, and construction of recycled water system facilities in Hawaii in cooperation with Hawaii Water Service Company, Waikoloa.\n\nThe federal share of each project is limited to 25%.\n\nInterior must: (1) enter into individual agreements with the Western Recycled Water Coalition participating agencies to fund such projects (as well as existing projects done in cooperation with the California cities of Palo Alto, Mountain View, Pittsburg, Antioch, Redwood City, and San Jose and the Delta Diablo Sanitation District, the North Coast County Water District, the South County Regional Wastewater Authority, and the Santa Clara Valley Water District); and (2) include in such agreements a provision for the reimbursement of design, planning, and construction costs.\n\nThe bill increases the authorization of appropriations for the recycled water system facilities of: (1) Antioch and the Delta Diablo Sanitation District, and (2) the South County Regional Wastewater Authority and the Santa Clara Valley Water District."
  }, 
  "titles": [
    {
      "as": "introduced", 
      "is_for_portion": false, 
      "title": "Western Water Recycling and Drought Relief Act", 
      "type": "short"
    }, 
    {
      "as": "introduced", 
      "is_for_portion": false, 
      "title": "Western Water Recycling and Drought Relief Act", 
      "type": "short"
    }, 
    {
      "as": "introduced", 
      "is_for_portion": false, 
      "title": "To amend the Reclamation Wastewater and Groundwater Study and Facilities Act to authorize certain recycled water projects, and for other purposes.", 
      "type": "official"
    }, 
    {
      "as": null, 
      "is_for_portion": false, 
      "title": "Western Water Recycling and Drought Relief Act", 
      "type": "display"
    }
  ], 
  "updated_at": "2017-09-11T02:39:22Z", 
  "url": "https://www.gpo.gov/fdsys/bulkdata/BILLSTATUS/115/hr/BILLSTATUS-115hr2799.xml"
}