{
  "actions": [
    {
      "acted_at": "2017-01-03", 
      "action_code": "10000", 
      "references": [], 
      "text": "Introduced in Senate", 
      "type": "action"
    }, 
    {
      "acted_at": "2017-01-03", 
      "action_code": "", 
      "committees": [
        "SSJU"
      ], 
      "references": [], 
      "status": "REFERRED", 
      "text": "Read twice and referred to the Committee on the Judiciary.", 
      "type": "referral"
    }
  ], 
  "amendments": [], 
  "bill_id": "sjres2-115", 
  "bill_type": "sjres", 
  "by_request": false, 
  "committee_reports": [], 
  "committees": [
    {
      "activity": [
        "referral"
      ], 
      "committee": "Senate Judiciary", 
      "committee_id": "SSJU"
    }
  ], 
  "congress": "115", 
  "cosponsors": [
    {
      "bioguide_id": "D000618", 
      "district": null, 
      "name": "Daines, Steve", 
      "original_cosponsor": false, 
      "sponsored_at": "2017-03-27", 
      "state": "MT", 
      "title": "Sen", 
      "withdrawn_at": null
    }, 
    {
      "bioguide_id": "F000463", 
      "district": null, 
      "name": "Fischer, Deb", 
      "original_cosponsor": true, 
      "sponsored_at": "2017-01-03", 
      "state": "NE", 
      "title": "Sen", 
      "withdrawn_at": null
    }, 
    {
      "bioguide_id": "J000293", 
      "district": null, 
      "name": "Johnson, Ron", 
      "original_cosponsor": true, 
      "sponsored_at": "2017-01-03", 
      "state": "WI", 
      "title": "Sen", 
      "withdrawn_at": null
    }, 
    {
      "bioguide_id": "K000393", 
      "district": null, 
      "name": "Kennedy, John", 
      "original_cosponsor": false, 
      "sponsored_at": "2017-02-06", 
      "state": "LA", 
      "title": "Sen", 
      "withdrawn_at": null
    }, 
    {
      "bioguide_id": "L000577", 
      "district": null, 
      "name": "Lee, Mike", 
      "original_cosponsor": true, 
      "sponsored_at": "2017-01-03", 
      "state": "UT", 
      "title": "Sen", 
      "withdrawn_at": null
    }, 
    {
      "bioguide_id": "P000603", 
      "district": null, 
      "name": "Paul, Rand", 
      "original_cosponsor": false, 
      "sponsored_at": "2017-03-30", 
      "state": "KY", 
      "title": "Sen", 
      "withdrawn_at": null
    }, 
    {
      "bioguide_id": "P000612", 
      "district": null, 
      "name": "Perdue, David", 
      "original_cosponsor": true, 
      "sponsored_at": "2017-01-03", 
      "state": "GA", 
      "title": "Sen", 
      "withdrawn_at": null
    }, 
    {
      "bioguide_id": "R000595", 
      "district": null, 
      "name": "Rubio, Marco", 
      "original_cosponsor": true, 
      "sponsored_at": "2017-01-03", 
      "state": "FL", 
      "title": "Sen", 
      "withdrawn_at": null
    }, 
    {
      "bioguide_id": "S001197", 
      "district": null, 
      "name": "Sasse, Ben", 
      "original_cosponsor": false, 
      "sponsored_at": "2017-01-04", 
      "state": "NE", 
      "title": "Sen", 
      "withdrawn_at": null
    }, 
    {
      "bioguide_id": "T000476", 
      "district": null, 
      "name": "Tillis, Thom", 
      "original_cosponsor": true, 
      "sponsored_at": "2017-01-03", 
      "state": "NC", 
      "title": "Sen", 
      "withdrawn_at": null
    }, 
    {
      "bioguide_id": "T000461", 
      "district": null, 
      "name": "Toomey, Pat", 
      "original_cosponsor": false, 
      "sponsored_at": "2017-01-30", 
      "state": "PA", 
      "title": "Sen", 
      "withdrawn_at": null
    }, 
    {
      "bioguide_id": "Y000064", 
      "district": null, 
      "name": "Young, Todd C.", 
      "original_cosponsor": false, 
      "sponsored_at": "2017-01-09", 
      "state": "IN", 
      "title": "Sen", 
      "withdrawn_at": null
    }
  ], 
  "enacted_as": null, 
  "history": {
    "active": false, 
    "awaiting_signature": false, 
    "enacted": false, 
    "vetoed": false
  }, 
  "introduced_at": "2017-01-03", 
  "number": "2", 
  "official_title": "A joint resolution proposing an amendment to the Constitution of the United States relative to limiting the number of terms that a Member of Congress may serve.", 
  "popular_title": null, 
  "related_bills": [
    {
      "bill_id": "hjres17-115", 
      "identified_by": "CRS", 
      "reason": "related", 
      "type": "bill"
    }, 
    {
      "bill_id": "hjres23-115", 
      "identified_by": "CRS", 
      "reason": "related", 
      "type": "bill"
    }, 
    {
      "bill_id": "hjres6-115", 
      "identified_by": "CRS", 
      "reason": "related", 
      "type": "bill"
    }
  ], 
  "short_title": null, 
  "sponsor": {
    "bioguide_id": "C001098", 
    "district": null, 
    "name": "Cruz, Ted", 
    "state": "TX", 
    "title": "Sen", 
    "type": "person"
  }, 
  "status": "REFERRED", 
  "status_at": "2017-01-03", 
  "subjects": [
    "Congress", 
    "Congressional elections", 
    "Constitution and constitutional amendments", 
    "House of Representatives", 
    "Members of Congress", 
    "Senate"
  ], 
  "subjects_top_term": "Congress", 
  "summary": {
    "as": "Introduced in Senate", 
    "date": "2017-01-03T05:00:00Z", 
    "text": "Constitutional Amendment\n\n This joint resolution proposes a constitutional amendment limiting Members of the House of Representatives to three terms and Members of the Senate to two terms."
  }, 
  "titles": [
    {
      "as": "introduced", 
      "is_for_portion": false, 
      "title": "A joint resolution proposing an amendment to the Constitution of the United States relative to limiting the number of terms that a Member of Congress may serve.", 
      "type": "official"
    }, 
    {
      "as": null, 
      "is_for_portion": false, 
      "title": "A joint resolution proposing an amendment to the Constitution of the United States relative to limiting the number of terms that a Member of Congress may serve.", 
      "type": "display"
    }
  ], 
  "updated_at": "2017-07-20T18:46:15Z", 
  "url": "https://www.gpo.gov/fdsys/bulkdata/BILLSTATUS/115/sjres/BILLSTATUS-115sjres2.xml"
}