<?xml version="1.0" encoding="UTF-8"?>
<billStatus>
  <bill>
    <relatedBills />
    <sponsors>
      <item>
        <bioguideId>S001191</bioguideId>
        <state>AZ</state>
        <fullName>Rep. Sinema, Kyrsten [D-AZ-9]</fullName>
        <identifiers>
          <bioguideId>S001191</bioguideId>
          <lisID>2099</lisID>
          <gpoId />
        </identifiers>
        <party>D</party>
        <district>9</district>
        <byRequestType />
        <middleName />
        <lastName>Sinema</lastName>
        <firstName>Kyrsten</firstName>
      </item>
    </sponsors>
    <updateDate>2017-06-19T21:30:17Z</updateDate>
    <recordedVotes />
    <notes />
    <introducedDate>2017-03-17</introducedDate>
    <calendarNumbers />
    <laws />
    <version>1.0.0</version>
    <committeeReports />
    <originChamber>House</originChamber>
    <summaries>
      <billSummaries>
        <item>
          <lastSummaryUpdateDate>2017-04-26T16:37:21Z</lastSummaryUpdateDate>
          <actionDesc>Introduced in House</actionDesc>
          <actionDate>2017-03-17</actionDate>
          <updateDate>2017-03-17T04:00:00Z</updateDate>
          <versionCode>00</versionCode>
          <name>Introduced in House</name>
          <text><![CDATA[<p><strong>Student Testing Improvement and Accountability Act</strong></p> <p>This bill amends the Elementary and Secondary Education Act of 1965 to reduce the required frequency of student achievement tests in mathematics and reading or language arts. Currently, students must be tested in those areas against state academic content and achievement standards in each of grades three through eight. This bill instead requires that those tests be administered at least once during: (1) grades 3 through 5, (2) grades 6 through 9, and (3) grades 10 through 12. </p>]]></text>
        </item>
      </billSummaries>
    </summaries>
    <titles>
      <item>
        <titleType>(Extracted from GPO) Short Titles as Introduced</titleType>
        <title>Student Testing Improvement and Accountability Act</title>
        <chamberCode />
        <parentTitleType />
        <chamberName />
      </item>
      <item>
        <titleType>Short Titles as Introduced</titleType>
        <title>Student Testing Improvement and Accountability Act</title>
        <chamberCode />
        <parentTitleType />
        <chamberName />
      </item>
      <item>
        <titleType>Official Title as Introduced</titleType>
        <title>To amend the Elementary and Secondary Education Act of 1965 to clarify when certain academic assessments shall be administered.</title>
        <chamberCode />
        <parentTitleType />
        <chamberName />
      </item>
      <item>
        <titleType>Display Title</titleType>
        <title>Student Testing Improvement and Accountability Act</title>
        <chamberCode />
        <parentTitleType />
        <chamberName />
      </item>
    </titles>
    <billType>HR</billType>
    <amendments />
    <actions>
      <item>
        <sourceSystem>
          <code>2</code>
          <name>House floor actions</name>
        </sourceSystem>
        <actionCode>H11100</actionCode>
        <links />
        <committee>
          <name>Education and the Workforce Committee</name>
          <systemCode>hsed00</systemCode>
        </committee>
        <actionDate>2017-03-17</actionDate>
        <type>IntroReferral</type>
        <text>Referred to the House Committee on Education and the Workforce.</text>
      </item>
      <item>
        <sourceSystem>
          <code>9</code>
          <name>Library of Congress</name>
        </sourceSystem>
        <actionCode>Intro-H</actionCode>
        <links />
        <committee />
        <actionDate>2017-03-17</actionDate>
        <type>IntroReferral</type>
        <text>Introduced in House</text>
      </item>
      <item>
        <sourceSystem>
          <code>9</code>
          <name>Library of Congress</name>
        </sourceSystem>
        <actionCode>1000</actionCode>
        <links />
        <committee />
        <actionDate>2017-03-17</actionDate>
        <type>IntroReferral</type>
        <text>Introduced in House</text>
      </item>
      <actionTypeCounts>
        <introducedInTheHouse>1</introducedInTheHouse>
        <billReferrals>1</billReferrals>
        <introducedInHouse>1</introducedInHouse>
      </actionTypeCounts>
      <actionByCounts>
        <houseOfRepresentatives>3</houseOfRepresentatives>
      </actionByCounts>
    </actions>
    <latestAction>
      <actionDate>2017-03-17</actionDate>
      <links />
      <text>Referred to the House Committee on Education and the Workforce.</text>
    </latestAction>
    <billNumber>1601</billNumber>
    <congress>115</congress>
    <title>Student Testing Improvement and Accountability Act</title>
    <policyArea>
      <name>Education</name>
    </policyArea>
    <subjects>
      <billSubjects>
        <policyArea>
          <name>Education</name>
        </policyArea>
        <legislativeSubjects>
          <item>
            <name>Academic performance and assessments</name>
          </item>
          <item>
            <name>Elementary and secondary education</name>
          </item>
          <item>
            <name>Language arts</name>
          </item>
        </legislativeSubjects>
      </billSubjects>
    </subjects>
    <cboCostEstimates />
    <cosponsors>
      <item>
        <state>NY</state>
        <firstName>Lee</firstName>
        <identifiers>
          <gpoId />
          <lisID>2261</lisID>
          <bioguideId>Z000017</bioguideId>
        </identifiers>
        <party>R</party>
        <sponsorshipDate>2017-03-17</sponsorshipDate>
        <middleName>M.</middleName>
        <sponsorshipWithdrawnDate />
        <lastName>Zeldin</lastName>
        <bioguideId>Z000017</bioguideId>
        <fullName>Rep. Zeldin, Lee M. [R-NY-1]</fullName>
        <isOriginalCosponsor>True</isOriginalCosponsor>
        <district>1</district>
      </item>
    </cosponsors>
    <committees>
      <billCommittees>
        <item>
          <type>Standing</type>
          <name>Education and the Workforce Committee</name>
          <chamber>House</chamber>
          <activities>
            <item>
              <name>Referred to</name>
              <date>2017-03-17T13:02:25Z</date>
            </item>
          </activities>
          <systemCode>hsed00</systemCode>
          <subcommittees />
        </item>
      </billCommittees>
    </committees>
    <constitutionalAuthorityStatementText><![CDATA[<pre>From the Congressional Record Online through the Government Publishing Office [<a href='http://www.gpo.gov'>www.gpo.gov</a>]By Ms. SINEMA:H.R. 1601.Congress has the power to enact this legislation pursuantto the following:Article 1, Section 8[Page H2184]</pre>]]></constitutionalAuthorityStatementText>
    <createDate>2017-03-18T04:55:14Z</createDate>
  </bill>
  <dublinCore xmlns:dc="http://purl.org/dc/elements/1.1/">
    <dc:format>text/xml</dc:format>
    <dc:language>EN</dc:language>
    <dc:rights>Pursuant to Title 17 Section 105 of the United States Code, this file is not subject to copyright protection and is in the public domain.</dc:rights>
    <dc:contributor>Congressional Research Service, Library of Congress</dc:contributor>
    <dc:description>This file contains bill summaries and statuses for federal legislation. A bill summary describes the most significant provisions of a piece of legislation and details the effects the legislative text may have on current law and federal programs. Bill summaries are authored by the Congressional Research Service (CRS) of the Library of Congress. As stated in Public Law 91-510 (2 USC 166 (d)(6)), one of the duties of CRS is "to prepare summaries and digests of bills and resolutions of a public general nature introduced in the Senate or House of Representatives". For more information, refer to the User Guide that accompanies this file.</dc:description>
  </dublinCore>
</billStatus>

