<bill session="115" type="h" number="3469" updated="2017-09-11T02:55:59Z">
  <state datetime="2017-07-27">REFERRED</state>
  <status>
    <introduced datetime="2017-07-27"/>
  </status>
  <introduced datetime="2017-07-27"/>
  <titles>
    <title type="official" as="introduced">To designate the bridge located in Blount County, Tennessee, on the Foothills Parkway (commonly known as "Bridge 2") as the "Dean Stone Bridge".</title>
    <title type="display">To designate the bridge located in Blount County, Tennessee, on the Foothills Parkway (commonly known as "Bridge 2") as the "Dean Stone Bridge".</title>
  </titles>
  <sponsor bioguide_id="D000533"/>
  <cosponsors/>
  <actions>
    <action datetime="2017-07-27">
      <text>Introduced in House</text>
    </action>
    <action datetime="2017-07-27" state="REFERRED">
      <text>Referred to the House Committee on Natural Resources.</text>
    </action>
    <action datetime="2017-08-14">
      <text>Referred to the Subcommittee on Federal Lands.</text>
    </action>
  </actions>
  <committees>
    <committee subcommittee="" code="HSII" name="House Natural Resources" activity="Referral"/>
    <committee subcommittee="Federal Lands" code="HSII10" name="House Natural Resources" activity="Referral"/>
  </committees>
  <relatedbills/>
  <subjects>
    <term name="Transportation and public works"/>
  </subjects>
  <amendments/>
  <committee-reports/>
</bill>
