{
  "actions": [
    {
      "acted_at": "2017-03-01", 
      "action_code": "Intro-H", 
      "references": [], 
      "text": "Introduced in House", 
      "type": "action"
    }, 
    {
      "acted_at": "2017-03-01", 
      "action_code": "H11100", 
      "committees": [
        "HSED"
      ], 
      "references": [], 
      "status": "REFERRED", 
      "text": "Referred to the House Committee on Education and the Workforce.", 
      "type": "referral"
    }
  ], 
  "amendments": [], 
  "bill_id": "hr1289-115", 
  "bill_type": "hr", 
  "by_request": false, 
  "committee_reports": [], 
  "committees": [
    {
      "activity": [
        "referral"
      ], 
      "committee": "House Education and the Workforce", 
      "committee_id": "HSED"
    }
  ], 
  "congress": "115", 
  "cosponsors": [
    {
      "bioguide_id": "B000490", 
      "district": "2", 
      "name": "Bishop, Sanford D., Jr.", 
      "original_cosponsor": true, 
      "sponsored_at": "2017-03-01", 
      "state": "GA", 
      "title": "Rep", 
      "withdrawn_at": null
    }, 
    {
      "bioguide_id": "B001245", 
      "district": null, 
      "name": "Bordallo, Madeleine Z.", 
      "original_cosponsor": true, 
      "sponsored_at": "2017-03-01", 
      "state": "GU", 
      "title": "Rep", 
      "withdrawn_at": null
    }, 
    {
      "bioguide_id": "B001285", 
      "district": "26", 
      "name": "Brownley, Julia", 
      "original_cosponsor": false, 
      "sponsored_at": "2017-07-20", 
      "state": "CA", 
      "title": "Rep", 
      "withdrawn_at": null
    }, 
    {
      "bioguide_id": "C001072", 
      "district": "7", 
      "name": "Carson, Andre", 
      "original_cosponsor": true, 
      "sponsored_at": "2017-03-01", 
      "state": "IN", 
      "title": "Rep", 
      "withdrawn_at": null
    }, 
    {
      "bioguide_id": "C001067", 
      "district": "9", 
      "name": "Clarke, Yvette D.", 
      "original_cosponsor": true, 
      "sponsored_at": "2017-03-01", 
      "state": "NY", 
      "title": "Rep", 
      "withdrawn_at": null
    }, 
    {
      "bioguide_id": "C000714", 
      "district": "13", 
      "name": "Conyers, John, Jr.", 
      "original_cosponsor": false, 
      "sponsored_at": "2017-03-21", 
      "state": "MI", 
      "title": "Rep", 
      "withdrawn_at": null
    }, 
    {
      "bioguide_id": "D000624", 
      "district": "12", 
      "name": "Dingell, Debbie", 
      "original_cosponsor": true, 
      "sponsored_at": "2017-03-01", 
      "state": "MI", 
      "title": "Rep", 
      "withdrawn_at": null
    }, 
    {
      "bioguide_id": "E000296", 
      "district": "2", 
      "name": "Evans, Dwight", 
      "original_cosponsor": false, 
      "sponsored_at": "2017-03-21", 
      "state": "PA", 
      "title": "Rep", 
      "withdrawn_at": null
    }, 
    {
      "bioguide_id": "G000535", 
      "district": "4", 
      "name": "Gutierrez, Luis V.", 
      "original_cosponsor": false, 
      "sponsored_at": "2017-03-21", 
      "state": "IL", 
      "title": "Rep", 
      "withdrawn_at": null
    }, 
    {
      "bioguide_id": "L000287", 
      "district": "5", 
      "name": "Lewis, John", 
      "original_cosponsor": true, 
      "sponsored_at": "2017-03-01", 
      "state": "GA", 
      "title": "Rep", 
      "withdrawn_at": null
    }, 
    {
      "bioguide_id": "L000570", 
      "district": "3", 
      "name": "Lujan, Ben Ray", 
      "original_cosponsor": false, 
      "sponsored_at": "2017-04-25", 
      "state": "NM", 
      "title": "Rep", 
      "withdrawn_at": null
    }, 
    {
      "bioguide_id": "N000147", 
      "district": null, 
      "name": "Norton, Eleanor Holmes", 
      "original_cosponsor": true, 
      "sponsored_at": "2017-03-01", 
      "state": "DC", 
      "title": "Rep", 
      "withdrawn_at": null
    }, 
    {
      "bioguide_id": "P000610", 
      "district": null, 
      "name": "Plaskett, Stacey E.", 
      "original_cosponsor": false, 
      "sponsored_at": "2017-03-21", 
      "state": "VI", 
      "title": "Rep", 
      "withdrawn_at": null
    }, 
    {
      "bioguide_id": "P000607", 
      "district": "2", 
      "name": "Pocan, Mark", 
      "original_cosponsor": false, 
      "sponsored_at": "2017-03-21", 
      "state": "WI", 
      "title": "Rep", 
      "withdrawn_at": null
    }, 
    {
      "bioguide_id": "R000602", 
      "district": "4", 
      "name": "Rice, Kathleen M.", 
      "original_cosponsor": true, 
      "sponsored_at": "2017-03-01", 
      "state": "NY", 
      "title": "Rep", 
      "withdrawn_at": null
    }, 
    {
      "bioguide_id": "S001170", 
      "district": "1", 
      "name": "Shea-Porter, Carol", 
      "original_cosponsor": false, 
      "sponsored_at": "2017-03-21", 
      "state": "NH", 
      "title": "Rep", 
      "withdrawn_at": null
    }, 
    {
      "bioguide_id": "S001200", 
      "district": "9", 
      "name": "Soto, Darren", 
      "original_cosponsor": true, 
      "sponsored_at": "2017-03-01", 
      "state": "FL", 
      "title": "Rep", 
      "withdrawn_at": null
    }, 
    {
      "bioguide_id": "T000465", 
      "district": "3", 
      "name": "Tsongas, Niki", 
      "original_cosponsor": true, 
      "sponsored_at": "2017-03-01", 
      "state": "MA", 
      "title": "Rep", 
      "withdrawn_at": null
    }, 
    {
      "bioguide_id": "Y000062", 
      "district": "3", 
      "name": "Yarmuth, John A.", 
      "original_cosponsor": false, 
      "sponsored_at": "2017-05-23", 
      "state": "KY", 
      "title": "Rep", 
      "withdrawn_at": null
    }
  ], 
  "enacted_as": null, 
  "history": {
    "active": false, 
    "awaiting_signature": false, 
    "enacted": false, 
    "vetoed": false
  }, 
  "introduced_at": "2017-03-01", 
  "number": "1289", 
  "official_title": "To establish the Social Work Reinvestment Commission to provide independent counsel to Congress and the Secretary of Health and Human Services on policy issues related to recruitment, retention, research, and reinvestment in the profession of social work, and for other purposes.", 
  "popular_title": null, 
  "related_bills": [], 
  "short_title": "Dorothy I. Height and Whitney M. Young, Jr., Social Work Reinvestment Act", 
  "sponsor": {
    "bioguide_id": "L000551", 
    "district": "13", 
    "name": "Lee, Barbara", 
    "state": "CA", 
    "title": "Rep", 
    "type": "person"
  }, 
  "status": "REFERRED", 
  "status_at": "2017-03-01", 
  "subjects": [
    "Advisory bodies", 
    "Congressional oversight", 
    "Department of Health and Human Services", 
    "Education programs funding", 
    "Executive agency funding and structure", 
    "Government information and archives", 
    "Government studies and investigations", 
    "Higher education", 
    "Licensing and registrations", 
    "Policy sciences", 
    "Public contracts and procurement", 
    "Research administration and funding", 
    "Social welfare", 
    "Social work, volunteer service, charitable organizations", 
    "Student aid and college costs", 
    "Wages and earnings", 
    "Worker safety and health"
  ], 
  "subjects_top_term": "Social welfare", 
  "summary": null, 
  "titles": [
    {
      "as": "introduced", 
      "is_for_portion": false, 
      "title": "Dorothy I. Height and Whitney M. Young, Jr., Social Work Reinvestment Act", 
      "type": "short"
    }, 
    {
      "as": "introduced", 
      "is_for_portion": false, 
      "title": "Dorothy I. Height and Whitney M. Young, Jr., Social Work Reinvestment Act", 
      "type": "short"
    }, 
    {
      "as": "introduced", 
      "is_for_portion": false, 
      "title": "To establish the Social Work Reinvestment Commission to provide independent counsel to Congress and the Secretary of Health and Human Services on policy issues related to recruitment, retention, research, and reinvestment in the profession of social work, and for other purposes.", 
      "type": "official"
    }, 
    {
      "as": null, 
      "is_for_portion": false, 
      "title": "Dorothy I. Height and Whitney M. Young, Jr., Social Work Reinvestment Act", 
      "type": "display"
    }
  ], 
  "updated_at": "2017-07-21T07:16:01Z", 
  "url": "https://www.gpo.gov/fdsys/bulkdata/BILLSTATUS/115/hr/BILLSTATUS-115hr1289.xml"
}