<?xml version="1.0" encoding="UTF-8"?>
<billStatus>
  <bill>
    <billType>SRES</billType>
    <calendarNumbers />
    <latestAction>
      <text>Referred to the Committee on Health, Education, Labor, and Pensions. (text of measure as introduced: CR S1895-1896)</text>
      <links />
      <actionDate>2017-03-21</actionDate>
    </latestAction>
    <introducedDate>2017-03-21</introducedDate>
    <congress>115</congress>
    <billNumber>91</billNumber>
    <committees>
      <billCommittees>
        <item>
          <subcommittees />
          <systemCode>sshr00</systemCode>
          <type>Standing</type>
          <name>Health, Education, Labor, and Pensions Committee</name>
          <activities>
            <item>
              <name>Referred to</name>
              <date>2017-03-21T18:58:58Z</date>
            </item>
          </activities>
          <chamber>Senate</chamber>
        </item>
      </billCommittees>
    </committees>
    <recordedVotes />
    <policyArea>
      <name>Social Welfare</name>
    </policyArea>
    <summaries>
      <billSummaries>
        <item>
          <updateDate>2017-03-21T04:00:00Z</updateDate>
          <versionCode>00</versionCode>
          <lastSummaryUpdateDate>2017-07-28T19:17:04Z</lastSummaryUpdateDate>
          <actionDesc>Introduced in Senate</actionDesc>
          <text><![CDATA[<p>Supports the goals and ideals of National Professional Social Work Month in March 2017 and World Social Work Day on March 21, 2017.</p>]]></text>
          <actionDate>2017-03-21</actionDate>
          <name>Introduced in Senate</name>
        </item>
      </billSummaries>
    </summaries>
    <cosponsors />
    <originChamber>Senate</originChamber>
    <title>A resolution supporting the goals and ideals of National Professional Social Work Month in March 2017 and World Social Work Day on March 21, 2017.</title>
    <subjects>
      <billSubjects>
        <legislativeSubjects>
          <item>
            <name>Commemorative events and holidays</name>
          </item>
          <item>
            <name>Congressional tributes</name>
          </item>
          <item>
            <name>Social work, volunteer service, charitable organizations</name>
          </item>
        </legislativeSubjects>
        <policyArea>
          <name>Social Welfare</name>
        </policyArea>
      </billSubjects>
    </subjects>
    <notes />
    <relatedBills>
      <item>
        <congress>115</congress>
        <number>217</number>
        <type>HRES</type>
        <latestTitle>Supporting the goals and ideals of Social Work Month and World Social Work Day.</latestTitle>
        <relationshipDetails>
          <item>
            <type>Related bill</type>
            <identifiedBy>CRS</identifiedBy>
          </item>
        </relationshipDetails>
        <latestAction>
          <text>Referred to the House Committee on Education and the Workforce.</text>
          <actionDate>2017-03-21</actionDate>
        </latestAction>
      </item>
    </relatedBills>
    <cboCostEstimates />
    <amendments />
    <updateDate>2017-09-11T02:39:34Z</updateDate>
    <titles>
      <item>
        <parentTitleType />
        <title>A resolution supporting the goals and ideals of National Professional Social Work Month in March 2017 and World Social Work Day on March 21, 2017.</title>
        <titleType>Official Title as Introduced</titleType>
        <chamberCode />
        <chamberName />
      </item>
      <item>
        <parentTitleType />
        <title>A resolution supporting the goals and ideals of National Professional Social Work Month in March 2017 and World Social Work Day on March 21, 2017.</title>
        <titleType>Display Title</titleType>
        <chamberCode />
        <chamberName />
      </item>
    </titles>
    <laws />
    <sponsors>
      <item>
        <bioguideId>S000770</bioguideId>
        <identifiers>
          <bioguideId>S000770</bioguideId>
          <gpoId>8261</gpoId>
          <lisID>1531</lisID>
        </identifiers>
        <party>D</party>
        <fullName>Sen. Stabenow, Debbie [D-MI]</fullName>
        <lastName>STABENOW</lastName>
        <firstName>DEBORAH</firstName>
        <state>MI</state>
        <byRequestType />
        <middleName>ANN</middleName>
      </item>
    </sponsors>
    <actions>
      <item>
        <actionDate>2017-03-21</actionDate>
        <committee>
          <systemCode>sshr00</systemCode>
          <name>Health, Education, Labor, and Pensions Committee</name>
        </committee>
        <links>
          <link>
            <name>S1895-1896</name>
            <url>https://www.congress.gov/congressional-record/volume-163/senate-section/page/S1895-1896</url>
          </link>
        </links>
        <sourceSystem>
          <code>0</code>
          <name>Senate</name>
        </sourceSystem>
        <text>Referred to the Committee on Health, Education, Labor, and Pensions. (text of measure as introduced: CR S1895-1896)</text>
        <type>IntroReferral</type>
      </item>
      <item>
        <text>Introduced in Senate</text>
        <sourceSystem>
          <code>9</code>
          <name>Library of Congress</name>
        </sourceSystem>
        <links />
        <type>IntroReferral</type>
        <actionCode>10000</actionCode>
        <actionDate>2017-03-21</actionDate>
        <committee />
      </item>
      <actionTypeCounts>
        <introducedInSenate>1</introducedInSenate>
        <referredToCommittee>1</referredToCommittee>
      </actionTypeCounts>
      <actionByCounts>
        <senate>2</senate>
      </actionByCounts>
    </actions>
    <createDate>2017-03-22T05:45:16Z</createDate>
    <committeeReports />
    <version>1.0.0</version>
  </bill>
  <dublinCore xmlns:dc="http://purl.org/dc/elements/1.1/">
    <dc:format>text/xml</dc:format>
    <dc:language>EN</dc:language>
    <dc:rights>Pursuant to Title 17 Section 105 of the United States Code, this file is not subject to copyright protection and is in the public domain.</dc:rights>
    <dc:contributor>Congressional Research Service, Library of Congress</dc:contributor>
    <dc:description>This file contains bill summaries and statuses for federal legislation. A bill summary describes the most significant provisions of a piece of legislation and details the effects the legislative text may have on current law and federal programs. Bill summaries are authored by the Congressional Research Service (CRS) of the Library of Congress. As stated in Public Law 91-510 (2 USC 166 (d)(6)), one of the duties of CRS is "to prepare summaries and digests of bills and resolutions of a public general nature introduced in the Senate or House of Representatives". For more information, refer to the User Guide that accompanies this file.</dc:description>
  </dublinCore>
</billStatus>

