{
  "actions": [
    {
      "acted_at": "2017-07-26", 
      "action_code": "Intro-H", 
      "references": [], 
      "text": "Introduced in House", 
      "type": "action"
    }, 
    {
      "acted_at": "2017-07-26", 
      "action_code": "H11100", 
      "committees": [
        "HSPW"
      ], 
      "references": [], 
      "status": "REFERRED", 
      "text": "Referred to the House Committee on Transportation and Infrastructure.", 
      "type": "referral"
    }, 
    {
      "acted_at": "2017-07-27", 
      "action_code": "", 
      "committees": [
        "HSPW"
      ], 
      "references": [], 
      "text": "Referred to the Subcommittee on Railroads, Pipelines, and Hazardous Materials.", 
      "type": "referral"
    }
  ], 
  "amendments": [], 
  "bill_id": "hr3435-115", 
  "bill_type": "hr", 
  "by_request": false, 
  "committee_reports": [], 
  "committees": [
    {
      "activity": [
        "referral"
      ], 
      "committee": "House Transportation and Infrastructure", 
      "committee_id": "HSPW"
    }, 
    {
      "activity": [
        "referral"
      ], 
      "committee": "House Transportation and Infrastructure", 
      "committee_id": "HSPW", 
      "subcommittee": "Subcommittee on Railroads, Pipelines, and Hazardous Materials", 
      "subcommittee_id": "14"
    }
  ], 
  "congress": "115", 
  "cosponsors": [
    {
      "bioguide_id": "G000559", 
      "district": "3", 
      "name": "Garamendi, John", 
      "original_cosponsor": true, 
      "sponsored_at": "2017-07-26", 
      "state": "CA", 
      "title": "Rep", 
      "withdrawn_at": null
    }
  ], 
  "enacted_as": null, 
  "history": {
    "active": false, 
    "awaiting_signature": false, 
    "enacted": false, 
    "vetoed": false
  }, 
  "introduced_at": "2017-07-26", 
  "number": "3435", 
  "official_title": "To prohibit the transportation of certain volatile crude oil by rail.", 
  "popular_title": null, 
  "related_bills": [], 
  "short_title": null, 
  "sponsor": {
    "bioguide_id": "L000480", 
    "district": "17", 
    "name": "Lowey, Nita M.", 
    "state": "NY", 
    "title": "Rep", 
    "type": "person"
  }, 
  "status": "REFERRED", 
  "status_at": "2017-07-26", 
  "subjects": [
    "Transportation and public works"
  ], 
  "subjects_top_term": "Transportation and public works", 
  "summary": null, 
  "titles": [
    {
      "as": "introduced", 
      "is_for_portion": false, 
      "title": "To prohibit the transportation of certain volatile crude oil by rail.", 
      "type": "official"
    }, 
    {
      "as": null, 
      "is_for_portion": false, 
      "title": "To prohibit the transportation of certain volatile crude oil by rail.", 
      "type": "display"
    }
  ], 
  "updated_at": "2017-09-11T02:55:54Z", 
  "url": "https://www.gpo.gov/fdsys/bulkdata/BILLSTATUS/115/hr/BILLSTATUS-115hr3435.xml"
}