{
  "actions": [
    {
      "acted_at": "2017-01-09", 
      "action_code": "Intro-H", 
      "references": [], 
      "text": "Introduced in House", 
      "type": "action"
    }, 
    {
      "acted_at": "2017-01-09", 
      "action_code": "H11100", 
      "committees": [
        "HSBA"
      ], 
      "references": [], 
      "status": "REFERRED", 
      "text": "Referred to the House Committee on Financial Services.", 
      "type": "referral"
    }
  ], 
  "amendments": [], 
  "bill_id": "hr385-115", 
  "bill_type": "hr", 
  "by_request": false, 
  "committee_reports": [], 
  "committees": [
    {
      "activity": [
        "referral"
      ], 
      "committee": "House Financial Services", 
      "committee_id": "HSBA"
    }
  ], 
  "congress": "115", 
  "cosponsors": [
    {
      "bioguide_id": "S001177", 
      "district": null, 
      "name": "Sablan, Gregorio Kilili Camacho", 
      "original_cosponsor": true, 
      "sponsored_at": "2017-01-09", 
      "state": "MP", 
      "title": "Rep", 
      "withdrawn_at": null
    }
  ], 
  "enacted_as": null, 
  "history": {
    "active": false, 
    "awaiting_signature": false, 
    "enacted": false, 
    "vetoed": false
  }, 
  "introduced_at": "2017-01-09", 
  "number": "385", 
  "official_title": "To amend the Expedited Funds Availability Act to clarify the application of that Act to American Samoa and the Northern Mariana Islands.", 
  "popular_title": null, 
  "related_bills": [], 
  "short_title": null, 
  "sponsor": {
    "bioguide_id": "R000600", 
    "district": null, 
    "name": "Radewagen, Aumua Amata Coleman", 
    "state": "AS", 
    "title": "Rep", 
    "type": "person"
  }, 
  "status": "REFERRED", 
  "status_at": "2017-01-09", 
  "subjects": [
    "American Samoa", 
    "Bank accounts, deposits, capital", 
    "Finance and financial sector", 
    "Northern Mariana Islands", 
    "U.S. territories and protectorates"
  ], 
  "subjects_top_term": "Finance and financial sector", 
  "summary": {
    "as": "Introduced in House", 
    "date": "2017-01-09T05:00:00Z", 
    "text": "This bill amends the Expedited Funds Availability Act to apply the Act, which governs\u00a0bank deposit holds,\u00a0to American Samoa and the Commonwealth of the Northern Mariana Islands.\n\nThe Act's one-day extension for certain deposits in noncontiguous states or territories\u00a0shall apply\u00a0to both American Samoa and the Commonwealth of the Northern Mariana Islands."
  }, 
  "titles": [
    {
      "as": "introduced", 
      "is_for_portion": false, 
      "title": "To amend the Expedited Funds Availability Act to clarify the application of that Act to American Samoa and the Northern Mariana Islands.", 
      "type": "official"
    }, 
    {
      "as": null, 
      "is_for_portion": false, 
      "title": "To amend the Expedited Funds Availability Act to clarify the application of that Act to American Samoa and the Northern Mariana Islands.", 
      "type": "display"
    }
  ], 
  "updated_at": "2017-06-02T17:15:08Z", 
  "url": "https://www.gpo.gov/fdsys/bulkdata/BILLSTATUS/115/hr/BILLSTATUS-115hr385.xml"
}