<bill session="115" type="hj" number="6" updated="2017-10-13T07:15:46Z">
  <state datetime="2017-01-03">REFERRED</state>
  <status>
    <introduced datetime="2017-01-03"/>
  </status>
  <introduced datetime="2017-01-03"/>
  <titles>
    <title type="official" as="introduced">Proposing an amendment to the Constitution of the United States to limit the number of terms that a Member of Congress may serve.</title>
    <title type="display">Proposing an amendment to the Constitution of the United States to limit the number of terms that a Member of Congress may serve.</title>
  </titles>
  <sponsor bioguide_id="D000621"/>
  <cosponsors>
    <cosponsor bioguide_id="A000372" joined="2017-01-30"/>
    <cosponsor bioguide_id="B001298" joined="2017-01-09"/>
    <cosponsor bioguide_id="B001302" joined="2017-01-04"/>
    <cosponsor bioguide_id="B001294" joined="2017-01-03"/>
    <cosponsor bioguide_id="B001290" joined="2017-03-13"/>
    <cosponsor bioguide_id="B001274" joined="2017-10-12"/>
    <cosponsor bioguide_id="B001297" joined="2017-01-06"/>
    <cosponsor bioguide_id="B001305" joined="2017-02-13"/>
    <cosponsor bioguide_id="C001108" joined="2017-02-15"/>
    <cosponsor bioguide_id="D000626" joined="2017-01-30"/>
    <cosponsor bioguide_id="D000616" joined="2017-01-04"/>
    <cosponsor bioguide_id="D000615" joined="2017-01-10"/>
    <cosponsor bioguide_id="F000464" joined="2017-05-01"/>
    <cosponsor bioguide_id="F000465" joined="2017-03-22"/>
    <cosponsor bioguide_id="G000578" joined="2017-01-31"/>
    <cosponsor bioguide_id="G000584" joined="2017-06-21"/>
    <cosponsor bioguide_id="G000566" joined="2017-01-30"/>
    <cosponsor bioguide_id="H001074" joined="2017-06-06"/>
    <cosponsor bioguide_id="H001067" joined="2017-02-03"/>
    <cosponsor bioguide_id="J000299" joined="2017-03-17"/>
    <cosponsor bioguide_id="L000585" joined="2017-03-27"/>
    <cosponsor bioguide_id="L000491" joined="2017-03-22"/>
    <cosponsor bioguide_id="M001198" joined="2017-03-07"/>
    <cosponsor bioguide_id="M001184" joined="2017-01-30"/>
    <cosponsor bioguide_id="M001199" joined="2017-02-01"/>
    <cosponsor bioguide_id="M001187" joined="2017-01-09"/>
    <cosponsor bioguide_id="M001195" joined="2017-01-30"/>
    <cosponsor bioguide_id="N000190" joined="2017-07-20"/>
    <cosponsor bioguide_id="O000170" joined="2017-01-30"/>
    <cosponsor bioguide_id="P000609" joined="2017-02-13"/>
    <cosponsor bioguide_id="P000606" joined="2017-03-13"/>
    <cosponsor bioguide_id="R000601" joined="2017-01-31"/>
    <cosponsor bioguide_id="R000592" joined="2017-06-26"/>
    <cosponsor bioguide_id="R000583" joined="2017-02-06"/>
    <cosponsor bioguide_id="S000051" joined="2017-01-03"/>
    <cosponsor bioguide_id="S001183" joined="2017-01-30"/>
    <cosponsor bioguide_id="W000812" joined="2017-01-03"/>
    <cosponsor bioguide_id="Z000017" joined="2017-02-01"/>
  </cosponsors>
  <actions>
    <action datetime="2017-01-03">
      <text>Introduced in House</text>
    </action>
    <action datetime="2017-01-03" state="REFERRED">
      <text>Referred to the House Committee on the Judiciary.</text>
    </action>
    <action datetime="2017-01-11">
      <text>Referred to the Subcommittee on the Constitution and Civil Justice.</text>
    </action>
  </actions>
  <committees>
    <committee subcommittee="" code="HSJU" name="House Judiciary" activity="Referral"/>
    <committee subcommittee="Constitution and Civil Justice" code="HSJU10" name="House Judiciary" activity="Referral"/>
  </committees>
  <relatedbills>
    <bill type="hj" session="115" relation="unknown" number="13"/>
    <bill type="hj" session="115" relation="unknown" number="17"/>
    <bill type="hj" session="115" relation="unknown" number="20"/>
    <bill type="hj" session="115" relation="unknown" number="23"/>
    <bill type="hj" session="115" relation="unknown" number="101"/>
    <bill type="sj" session="115" relation="unknown" number="2"/>
  </relatedbills>
  <subjects>
    <term name="Congress"/>
    <term name="Congressional elections"/>
    <term name="Constitution and constitutional amendments"/>
    <term name="House of Representatives"/>
    <term name="Members of Congress"/>
    <term name="Senate"/>
  </subjects>
  <amendments/>
  <summary date="2017-01-03T05:00:00Z" status="Introduced in House">Constitutional Amendment

This joint resolution proposes a constitutional amendment limiting Members of the House of Representatives to three terms and Members of the Senate to two terms.</summary>
  <committee-reports/>
</bill>
