{
  "actions": [
    {
      "acted_at": "2017-09-28", 
      "action_code": "10000", 
      "references": [], 
      "text": "Introduced in Senate", 
      "type": "action"
    }, 
    {
      "acted_at": "2017-09-28", 
      "action_code": "", 
      "how": "by Unanimous Consent", 
      "references": [
        {
          "reference": "CR S6234", 
          "type": "consideration"
        }, 
        {
          "reference": "CR S6231", 
          "type": "text"
        }
      ], 
      "result": "pass", 
      "status": "PASSED:SIMPLERES", 
      "text": "Submitted in the Senate, considered, and agreed to without amendment and with a preamble by Unanimous Consent.", 
      "type": "vote", 
      "vote_type": "vote", 
      "where": "s"
    }
  ], 
  "amendments": [], 
  "bill_id": "sres275-115", 
  "bill_type": "sres", 
  "by_request": false, 
  "committee_reports": [], 
  "committees": [], 
  "congress": "115", 
  "cosponsors": [
    {
      "bioguide_id": "D000563", 
      "district": null, 
      "name": "Durbin, Richard J.", 
      "original_cosponsor": true, 
      "sponsored_at": "2017-09-28", 
      "state": "IL", 
      "title": "Sen", 
      "withdrawn_at": null
    }
  ], 
  "enacted_as": null, 
  "history": {
    "active": true, 
    "active_at": "2017-09-28", 
    "awaiting_signature": false, 
    "enacted": false, 
    "senate_passage_result": "pass", 
    "senate_passage_result_at": "2017-09-28", 
    "vetoed": false
  }, 
  "introduced_at": "2017-09-28", 
  "number": "275", 
  "official_title": "A resolution congratulating Northeastern Illinois University on the sesquicentennial of the University.", 
  "popular_title": null, 
  "related_bills": [
    {
      "bill_id": "hres543-115", 
      "identified_by": "CRS", 
      "reason": "identical", 
      "type": "bill"
    }
  ], 
  "short_title": null, 
  "sponsor": {
    "bioguide_id": "D000622", 
    "district": null, 
    "name": "Duckworth, Tammy", 
    "state": "IL", 
    "title": "Sen", 
    "type": "person"
  }, 
  "status": "PASSED:SIMPLERES", 
  "status_at": "2017-09-28", 
  "subjects": [
    "Commemorative events and holidays", 
    "Congressional tributes", 
    "Education", 
    "Educational facilities and institutions", 
    "Higher education", 
    "Illinois"
  ], 
  "subjects_top_term": "Education", 
  "summary": null, 
  "titles": [
    {
      "as": "introduced", 
      "is_for_portion": false, 
      "title": "A resolution congratulating Northeastern Illinois University on the sesquicentennial of the University.", 
      "type": "official"
    }, 
    {
      "as": null, 
      "is_for_portion": false, 
      "title": "A resolution congratulating Northeastern Illinois University on the sesquicentennial of the University.", 
      "type": "display"
    }
  ], 
  "updated_at": "2017-10-12T04:41:28Z", 
  "url": "https://www.gpo.gov/fdsys/bulkdata/BILLSTATUS/115/sres/BILLSTATUS-115sres275.xml"
}