<bill session="115" type="h" number="1909" updated="2017-06-19T21:45:21Z">
  <state datetime="2017-04-05">REFERRED</state>
  <status>
    <introduced datetime="2017-04-05"/>
  </status>
  <introduced datetime="2017-04-05"/>
  <titles>
    <title type="short" as="introduced">Environmental Health Workforce Act of 2017</title>
    <title type="short" as="introduced">Environmental Health Workforce Act of 2017</title>
    <title type="official" as="introduced">To prioritize educating and training for existing and new environmental health professionals.</title>
    <title type="display">Environmental Health Workforce Act of 2017</title>
  </titles>
  <sponsor bioguide_id="L000581"/>
  <cosponsors>
    <cosponsor bioguide_id="B001227" joined="2017-04-05"/>
    <cosponsor bioguide_id="C001090" joined="2017-04-25"/>
    <cosponsor bioguide_id="C001068" joined="2017-04-05"/>
    <cosponsor bioguide_id="C000714" joined="2017-04-05"/>
    <cosponsor bioguide_id="E000296" joined="2017-04-05"/>
    <cosponsor bioguide_id="J000298" joined="2017-04-25"/>
    <cosponsor bioguide_id="J000288" joined="2017-04-25"/>
    <cosponsor bioguide_id="N000147" joined="2017-04-05"/>
    <cosponsor bioguide_id="R000606" joined="2017-04-25"/>
    <cosponsor bioguide_id="S000510" joined="2017-05-23"/>
    <cosponsor bioguide_id="W000822" joined="2017-04-05"/>
  </cosponsors>
  <actions>
    <action datetime="2017-04-05">
      <text>Introduced in House</text>
    </action>
    <action datetime="2017-04-05" state="REFERRED">
      <text>Referred to the Committee on Energy and Commerce, and in addition to the Committee on Education and the Workforce, for a period to be subsequently determined by the Speaker, in each case for consideration of such provisions as fall within the jurisdiction of the committee concerned.</text>
    </action>
    <action datetime="2017-04-05">
      <text>Referred to House Energy and Commerce</text>
    </action>
    <action datetime="2017-04-05">
      <text>Referred to House Education and the Workforce</text>
    </action>
    <action datetime="2017-04-07">
      <text>Referred to the Subcommittee on Health.</text>
    </action>
  </actions>
  <committees>
    <committee subcommittee="" code="HSIF" name="House Energy and Commerce" activity="Referral"/>
    <committee subcommittee="Health" code="HSIF14" name="House Energy and Commerce" activity="Referral"/>
    <committee subcommittee="" code="HSED" name="House Education and the Workforce" activity="Referral"/>
  </committees>
  <relatedbills/>
  <subjects>
    <term name="Health"/>
    <term name="Congressional oversight"/>
    <term name="Environmental health"/>
    <term name="Health personnel"/>
    <term name="Higher education"/>
    <term name="Licensing and registrations"/>
    <term name="Medical education"/>
    <term name="Performance measurement"/>
    <term name="State and local government operations"/>
    <term name="Student aid and college costs"/>
  </subjects>
  <amendments/>
  <committee-reports/>
</bill>
