{
  "actions": [
    {
      "acted_at": "2017-05-24", 
      "action_code": "10000", 
      "references": [], 
      "text": "Introduced in Senate", 
      "type": "action"
    }, 
    {
      "acted_at": "2017-05-24", 
      "action_code": "", 
      "committees": [
        "SSFI"
      ], 
      "references": [], 
      "status": "REFERRED", 
      "text": "Read twice and referred to the Committee on Finance.", 
      "type": "referral"
    }
  ], 
  "amendments": [], 
  "bill_id": "s1210-115", 
  "bill_type": "s", 
  "by_request": false, 
  "committee_reports": [], 
  "committees": [
    {
      "activity": [
        "referral"
      ], 
      "committee": "Senate Finance", 
      "committee_id": "SSFI"
    }
  ], 
  "congress": "115", 
  "cosponsors": [
    {
      "bioguide_id": "H001061", 
      "district": null, 
      "name": "Hoeven, John", 
      "original_cosponsor": true, 
      "sponsored_at": "2017-05-24", 
      "state": "ND", 
      "title": "Sen", 
      "withdrawn_at": null
    }
  ], 
  "enacted_as": null, 
  "history": {
    "active": false, 
    "awaiting_signature": false, 
    "enacted": false, 
    "vetoed": false
  }, 
  "introduced_at": "2017-05-24", 
  "number": "1210", 
  "official_title": "A bill to amend the Internal Revenue Code of 1986 to reduce tax rates across the board.", 
  "popular_title": null, 
  "related_bills": [], 
  "short_title": null, 
  "sponsor": {
    "bioguide_id": "R000605", 
    "district": null, 
    "name": "Rounds, Mike", 
    "state": "SD", 
    "title": "Sen", 
    "type": "person"
  }, 
  "status": "REFERRED", 
  "status_at": "2017-05-24", 
  "subjects": [
    "Taxation"
  ], 
  "subjects_top_term": "Taxation", 
  "summary": {
    "as": "Introduced in Senate", 
    "date": "2017-05-24T04:00:00Z", 
    "text": "This bill amends the Internal Revenue Code to reduce the individual and corporate income tax rates by specified amounts."
  }, 
  "titles": [
    {
      "as": "introduced", 
      "is_for_portion": false, 
      "title": "A bill to amend the Internal Revenue Code of 1986 to reduce tax rates across the board.", 
      "type": "official"
    }, 
    {
      "as": null, 
      "is_for_portion": false, 
      "title": "A bill to amend the Internal Revenue Code of 1986 to reduce tax rates across the board.", 
      "type": "display"
    }
  ], 
  "updated_at": "2017-09-12T04:32:14Z", 
  "url": "https://www.gpo.gov/fdsys/bulkdata/BILLSTATUS/115/s/BILLSTATUS-115s1210.xml"
}