{
  "actions": [
    {
      "acted_at": "2017-07-20", 
      "action_code": "Intro-H", 
      "references": [], 
      "text": "Introduced in House", 
      "type": "action"
    }, 
    {
      "acted_at": "2017-07-20", 
      "action_code": "H11100", 
      "committees": [
        "HSJU"
      ], 
      "references": [], 
      "status": "REFERRED", 
      "text": "Referred to the House Committee on the Judiciary.", 
      "type": "referral"
    }
  ], 
  "amendments": [], 
  "bill_id": "hr3352-115", 
  "bill_type": "hr", 
  "by_request": false, 
  "committee_reports": [], 
  "committees": [
    {
      "activity": [
        "referral"
      ], 
      "committee": "House Judiciary", 
      "committee_id": "HSJU"
    }
  ], 
  "congress": "115", 
  "cosponsors": [
    {
      "bioguide_id": "C001066", 
      "district": "14", 
      "name": "Castor, Kathy", 
      "original_cosponsor": true, 
      "sponsored_at": "2017-07-20", 
      "state": "FL", 
      "title": "Rep", 
      "withdrawn_at": null
    }, 
    {
      "bioguide_id": "C001110", 
      "district": "46", 
      "name": "Correa, J. Luis", 
      "original_cosponsor": false, 
      "sponsored_at": "2017-10-04", 
      "state": "CA", 
      "title": "Rep", 
      "withdrawn_at": null
    }, 
    {
      "bioguide_id": "M000312", 
      "district": "2", 
      "name": "McGovern, James P.", 
      "original_cosponsor": false, 
      "sponsored_at": "2017-10-11", 
      "state": "MA", 
      "title": "Rep", 
      "withdrawn_at": null
    }, 
    {
      "bioguide_id": "R000602", 
      "district": "4", 
      "name": "Rice, Kathleen M.", 
      "original_cosponsor": false, 
      "sponsored_at": "2017-10-04", 
      "state": "NY", 
      "title": "Rep", 
      "withdrawn_at": null
    }, 
    {
      "bioguide_id": "V000130", 
      "district": "51", 
      "name": "Vargas, Juan", 
      "original_cosponsor": true, 
      "sponsored_at": "2017-07-20", 
      "state": "CA", 
      "title": "Rep", 
      "withdrawn_at": null
    }
  ], 
  "enacted_as": null, 
  "history": {
    "active": false, 
    "awaiting_signature": false, 
    "enacted": false, 
    "vetoed": false
  }, 
  "introduced_at": "2017-07-20", 
  "number": "3352", 
  "official_title": "To amend the Immigration and Nationality Act to provide that an applicant for citizenship who served honorably in the Armed Forces of the United States is not automatically barred from becoming a citizen of the United States for having committed certain crimes, and for other purposes.", 
  "popular_title": null, 
  "related_bills": [], 
  "short_title": "Second Chance for Service Act", 
  "sponsor": {
    "bioguide_id": "T000472", 
    "district": "41", 
    "name": "Takano, Mark", 
    "state": "CA", 
    "title": "Rep", 
    "type": "person"
  }, 
  "status": "REFERRED", 
  "status_at": "2017-07-20", 
  "subjects": [
    "Immigration"
  ], 
  "subjects_top_term": "Immigration", 
  "summary": null, 
  "titles": [
    {
      "as": "introduced", 
      "is_for_portion": false, 
      "title": "Second Chance for Service Act", 
      "type": "short"
    }, 
    {
      "as": "introduced", 
      "is_for_portion": false, 
      "title": "Second Chance for Service Act", 
      "type": "short"
    }, 
    {
      "as": "introduced", 
      "is_for_portion": false, 
      "title": "To amend the Immigration and Nationality Act to provide that an applicant for citizenship who served honorably in the Armed Forces of the United States is not automatically barred from becoming a citizen of the United States for having committed certain crimes, and for other purposes.", 
      "type": "official"
    }, 
    {
      "as": null, 
      "is_for_portion": false, 
      "title": "Second Chance for Service Act", 
      "type": "display"
    }
  ], 
  "updated_at": "2017-10-12T07:17:00Z", 
  "url": "https://www.gpo.gov/fdsys/bulkdata/BILLSTATUS/115/hr/BILLSTATUS-115hr3352.xml"
}