{
  "actions": [
    {
      "acted_at": "2017-04-06", 
      "action_code": "Intro-H", 
      "references": [], 
      "text": "Introduced in House", 
      "type": "action"
    }, 
    {
      "acted_at": "2017-04-06", 
      "action_code": "H11100", 
      "committees": [
        "HSBU"
      ], 
      "references": [], 
      "status": "REFERRED", 
      "text": "Referred to the House Committee on the Budget.", 
      "type": "referral"
    }
  ], 
  "amendments": [], 
  "bill_id": "hr1999-115", 
  "bill_type": "hr", 
  "by_request": false, 
  "committee_reports": [], 
  "committees": [
    {
      "activity": [
        "referral"
      ], 
      "committee": "House Budget", 
      "committee_id": "HSBU"
    }
  ], 
  "congress": "115", 
  "cosponsors": [
    {
      "bioguide_id": "B001291", 
      "district": "36", 
      "name": "Babin, Brian", 
      "original_cosponsor": true, 
      "sponsored_at": "2017-04-06", 
      "state": "TX", 
      "title": "Rep", 
      "withdrawn_at": null
    }, 
    {
      "bioguide_id": "B001302", 
      "district": "5", 
      "name": "Biggs, Andy", 
      "original_cosponsor": true, 
      "sponsored_at": "2017-04-06", 
      "state": "AZ", 
      "title": "Rep", 
      "withdrawn_at": null
    }, 
    {
      "bioguide_id": "B001290", 
      "district": "7", 
      "name": "Brat, Dave", 
      "original_cosponsor": true, 
      "sponsored_at": "2017-04-06", 
      "state": "VA", 
      "title": "Rep", 
      "withdrawn_at": null
    }, 
    {
      "bioguide_id": "C001103", 
      "district": "1", 
      "name": "Carter, Earl L. \"Buddy\"", 
      "original_cosponsor": false, 
      "sponsored_at": "2017-07-25", 
      "state": "GA", 
      "title": "Rep", 
      "withdrawn_at": null
    }, 
    {
      "bioguide_id": "C001053", 
      "district": "4", 
      "name": "Cole, Tom", 
      "original_cosponsor": false, 
      "sponsored_at": "2017-05-03", 
      "state": "OK", 
      "title": "Rep", 
      "withdrawn_at": null
    }, 
    {
      "bioguide_id": "D000616", 
      "district": "4", 
      "name": "DesJarlais, Scott", 
      "original_cosponsor": true, 
      "sponsored_at": "2017-04-06", 
      "state": "TN", 
      "title": "Rep", 
      "withdrawn_at": null
    }, 
    {
      "bioguide_id": "D000625", 
      "district": "11", 
      "name": "Donovan, Daniel M., Jr.", 
      "original_cosponsor": false, 
      "sponsored_at": "2017-05-01", 
      "state": "NY", 
      "title": "Rep", 
      "withdrawn_at": null
    }, 
    {
      "bioguide_id": "F000465", 
      "district": "3", 
      "name": "Ferguson, A. Drew, IV", 
      "original_cosponsor": false, 
      "sponsored_at": "2017-10-11", 
      "state": "GA", 
      "title": "Rep", 
      "withdrawn_at": null
    }, 
    {
      "bioguide_id": "G000565", 
      "district": "4", 
      "name": "Gosar, Paul A.", 
      "original_cosponsor": true, 
      "sponsored_at": "2017-04-06", 
      "state": "AZ", 
      "title": "Rep", 
      "withdrawn_at": null
    }, 
    {
      "bioguide_id": "G000568", 
      "district": "9", 
      "name": "Griffith, H. Morgan", 
      "original_cosponsor": true, 
      "sponsored_at": "2017-04-06", 
      "state": "VA", 
      "title": "Rep", 
      "withdrawn_at": null
    }, 
    {
      "bioguide_id": "G000576", 
      "district": "6", 
      "name": "Grothman, Glenn", 
      "original_cosponsor": true, 
      "sponsored_at": "2017-04-06", 
      "state": "WI", 
      "title": "Rep", 
      "withdrawn_at": null
    }, 
    {
      "bioguide_id": "H001071", 
      "district": "10", 
      "name": "Hice, Jody B.", 
      "original_cosponsor": true, 
      "sponsored_at": "2017-04-06", 
      "state": "GA", 
      "title": "Rep", 
      "withdrawn_at": null
    }, 
    {
      "bioguide_id": "M001187", 
      "district": "11", 
      "name": "Meadows, Mark", 
      "original_cosponsor": true, 
      "sponsored_at": "2017-04-06", 
      "state": "NC", 
      "title": "Rep", 
      "withdrawn_at": null
    }, 
    {
      "bioguide_id": "P000609", 
      "district": "6", 
      "name": "Palmer, Gary J.", 
      "original_cosponsor": true, 
      "sponsored_at": "2017-04-06", 
      "state": "AL", 
      "title": "Rep", 
      "withdrawn_at": null
    }, 
    {
      "bioguide_id": "P000605", 
      "district": "4", 
      "name": "Perry, Scott", 
      "original_cosponsor": true, 
      "sponsored_at": "2017-04-06", 
      "state": "PA", 
      "title": "Rep", 
      "withdrawn_at": null
    }, 
    {
      "bioguide_id": "P000598", 
      "district": "2", 
      "name": "Polis, Jared", 
      "original_cosponsor": true, 
      "sponsored_at": "2017-04-06", 
      "state": "CO", 
      "title": "Rep", 
      "withdrawn_at": null
    }, 
    {
      "bioguide_id": "R000586", 
      "district": "16", 
      "name": "Renacci, James B.", 
      "original_cosponsor": true, 
      "sponsored_at": "2017-04-06", 
      "state": "OH", 
      "title": "Rep", 
      "withdrawn_at": null
    }, 
    {
      "bioguide_id": "R000592", 
      "district": "4", 
      "name": "Rokita, Todd", 
      "original_cosponsor": false, 
      "sponsored_at": "2017-05-17", 
      "state": "IN", 
      "title": "Rep", 
      "withdrawn_at": null
    }, 
    {
      "bioguide_id": "S000051", 
      "district": "1", 
      "name": "Sanford, Mark", 
      "original_cosponsor": true, 
      "sponsored_at": "2017-04-06", 
      "state": "SC", 
      "title": "Rep", 
      "withdrawn_at": null
    }, 
    {
      "bioguide_id": "W000810", 
      "district": "7", 
      "name": "Woodall, Rob", 
      "original_cosponsor": false, 
      "sponsored_at": "2017-05-16", 
      "state": "GA", 
      "title": "Rep", 
      "withdrawn_at": null
    }
  ], 
  "enacted_as": null, 
  "history": {
    "active": false, 
    "awaiting_signature": false, 
    "enacted": false, 
    "vetoed": false
  }, 
  "introduced_at": "2017-04-06", 
  "number": "1999", 
  "official_title": "To require an annual report on offsets and pay-fors, and for other purposes.", 
  "popular_title": null, 
  "related_bills": [], 
  "short_title": "Federal Budget Accountability Act", 
  "sponsor": {
    "bioguide_id": "B001297", 
    "district": "4", 
    "name": "Buck, Ken", 
    "state": "CO", 
    "title": "Rep", 
    "type": "person"
  }, 
  "status": "REFERRED", 
  "status_at": "2017-04-06", 
  "subjects": [
    "Budget deficits and national debt", 
    "Budget process", 
    "Congressional oversight", 
    "Economics and public finance", 
    "Government information and archives"
  ], 
  "subjects_top_term": "Economics and public finance", 
  "summary": {
    "as": "Introduced in House", 
    "date": "2017-04-06T04:00:00Z", 
    "text": "Federal Budget Accountability Act \n\nThis bill requires the Office of Management and Budget (OMB) to report annually to Congress on the effect of provisions of legislation for the previous congressional session that were enacted to offset or pay for the costs of carrying out the legislation, including provisions that increase revenue, rescind budget authority, or reduce direct spending.\n\nThe OMB must also establish and report to Congress on a system to track the accuracy of the offsets and pay-fors. (Under the bill, an \"offset and pay-for\" is an estimate by the Congressional Budget Office for a provision of legislation that reduces spending, increases revenue, or reduces the deficit.)"
  }, 
  "titles": [
    {
      "as": "introduced", 
      "is_for_portion": false, 
      "title": "Federal Budget Accountability Act", 
      "type": "short"
    }, 
    {
      "as": "introduced", 
      "is_for_portion": false, 
      "title": "Federal Budget Accountability Act", 
      "type": "short"
    }, 
    {
      "as": "introduced", 
      "is_for_portion": false, 
      "title": "To require an annual report on offsets and pay-fors, and for other purposes.", 
      "type": "official"
    }, 
    {
      "as": null, 
      "is_for_portion": false, 
      "title": "Federal Budget Accountability Act", 
      "type": "display"
    }
  ], 
  "updated_at": "2017-10-12T07:16:32Z", 
  "url": "https://www.gpo.gov/fdsys/bulkdata/BILLSTATUS/115/hr/BILLSTATUS-115hr1999.xml"
}