{
  "actions": [
    {
      "acted_at": "2017-07-20", 
      "action_code": "Intro-H", 
      "references": [], 
      "text": "Introduced in House", 
      "type": "action"
    }, 
    {
      "acted_at": "2017-07-20", 
      "action_code": "H11100", 
      "committees": [
        "HSBA"
      ], 
      "references": [], 
      "status": "REFERRED", 
      "text": "Referred to the Committee on Financial Services, and in addition to the Committee on House Administration, for a period to be subsequently determined by the Speaker, in each case for consideration of such provisions as fall within the jurisdiction of the committee concerned.", 
      "type": "referral"
    }, 
    {
      "acted_at": "2017-07-20", 
      "action_code": "H11100", 
      "committees": [
        "HSHA"
      ], 
      "references": [], 
      "text": "Referred to the Committee on Financial Services, and in addition to the Committee on House Administration, for a period to be subsequently determined by the Speaker, in each case for consideration of such provisions as fall within the jurisdiction of the committee concerned.", 
      "type": "referral"
    }
  ], 
  "amendments": [], 
  "bill_id": "hr3334-115", 
  "bill_type": "hr", 
  "by_request": false, 
  "committee_reports": [], 
  "committees": [
    {
      "activity": [
        "referral"
      ], 
      "committee": "House Administration", 
      "committee_id": "HSHA"
    }, 
    {
      "activity": [
        "referral"
      ], 
      "committee": "House Financial Services", 
      "committee_id": "HSBA"
    }
  ], 
  "congress": "115", 
  "cosponsors": [
    {
      "bioguide_id": "C001061", 
      "district": "5", 
      "name": "Cleaver, Emanuel", 
      "original_cosponsor": true, 
      "sponsored_at": "2017-07-20", 
      "state": "MO", 
      "title": "Rep", 
      "withdrawn_at": null
    }, 
    {
      "bioguide_id": "C001068", 
      "district": "9", 
      "name": "Cohen, Steve", 
      "original_cosponsor": true, 
      "sponsored_at": "2017-07-20", 
      "state": "TN", 
      "title": "Rep", 
      "withdrawn_at": null
    }, 
    {
      "bioguide_id": "C000714", 
      "district": "13", 
      "name": "Conyers, John, Jr.", 
      "original_cosponsor": true, 
      "sponsored_at": "2017-07-20", 
      "state": "MI", 
      "title": "Rep", 
      "withdrawn_at": null
    }, 
    {
      "bioguide_id": "E000296", 
      "district": "2", 
      "name": "Evans, Dwight", 
      "original_cosponsor": false, 
      "sponsored_at": "2017-09-07", 
      "state": "PA", 
      "title": "Rep", 
      "withdrawn_at": null
    }, 
    {
      "bioguide_id": "F000455", 
      "district": "11", 
      "name": "Fudge, Marcia L.", 
      "original_cosponsor": true, 
      "sponsored_at": "2017-07-20", 
      "state": "OH", 
      "title": "Rep", 
      "withdrawn_at": null
    }, 
    {
      "bioguide_id": "G000553", 
      "district": "9", 
      "name": "Green, Al", 
      "original_cosponsor": true, 
      "sponsored_at": "2017-07-20", 
      "state": "TX", 
      "title": "Rep", 
      "withdrawn_at": null
    }, 
    {
      "bioguide_id": "J000294", 
      "district": "8", 
      "name": "Jeffries, Hakeem S.", 
      "original_cosponsor": true, 
      "sponsored_at": "2017-07-20", 
      "state": "NY", 
      "title": "Rep", 
      "withdrawn_at": null
    }, 
    {
      "bioguide_id": "K000009", 
      "district": "9", 
      "name": "Kaptur, Marcy", 
      "original_cosponsor": true, 
      "sponsored_at": "2017-07-20", 
      "state": "OH", 
      "title": "Rep", 
      "withdrawn_at": null
    }, 
    {
      "bioguide_id": "K000385", 
      "district": "2", 
      "name": "Kelly, Robin L.", 
      "original_cosponsor": true, 
      "sponsored_at": "2017-07-20", 
      "state": "IL", 
      "title": "Rep", 
      "withdrawn_at": null
    }, 
    {
      "bioguide_id": "L000551", 
      "district": "13", 
      "name": "Lee, Barbara", 
      "original_cosponsor": true, 
      "sponsored_at": "2017-07-20", 
      "state": "CA", 
      "title": "Rep", 
      "withdrawn_at": null
    }, 
    {
      "bioguide_id": "N000147", 
      "district": null, 
      "name": "Norton, Eleanor Holmes", 
      "original_cosponsor": true, 
      "sponsored_at": "2017-07-20", 
      "state": "DC", 
      "title": "Rep", 
      "withdrawn_at": null
    }, 
    {
      "bioguide_id": "R000515", 
      "district": "1", 
      "name": "Rush, Bobby L.", 
      "original_cosponsor": true, 
      "sponsored_at": "2017-07-20", 
      "state": "IL", 
      "title": "Rep", 
      "withdrawn_at": null
    }, 
    {
      "bioguide_id": "S001187", 
      "district": "15", 
      "name": "Stivers, Steve", 
      "original_cosponsor": true, 
      "sponsored_at": "2017-07-20", 
      "state": "OH", 
      "title": "Rep", 
      "withdrawn_at": null
    }, 
    {
      "bioguide_id": "V000131", 
      "district": "33", 
      "name": "Veasey, Marc A.", 
      "original_cosponsor": true, 
      "sponsored_at": "2017-07-20", 
      "state": "TX", 
      "title": "Rep", 
      "withdrawn_at": null
    }, 
    {
      "bioguide_id": "Y000062", 
      "district": "3", 
      "name": "Yarmuth, John A.", 
      "original_cosponsor": true, 
      "sponsored_at": "2017-07-20", 
      "state": "KY", 
      "title": "Rep", 
      "withdrawn_at": null
    }
  ], 
  "enacted_as": null, 
  "history": {
    "active": false, 
    "awaiting_signature": false, 
    "enacted": false, 
    "vetoed": false
  }, 
  "introduced_at": "2017-07-20", 
  "number": "3334", 
  "official_title": "To posthumously award a Congressional gold medal to Maya Angelou in recognition of her achievements and contributions to American culture and the civil rights movement.", 
  "popular_title": null, 
  "related_bills": [], 
  "short_title": "Maya Angelou Congressional Gold Medal Act", 
  "sponsor": {
    "bioguide_id": "B001281", 
    "district": "3", 
    "name": "Beatty, Joyce", 
    "state": "OH", 
    "title": "Rep", 
    "type": "person"
  }, 
  "status": "REFERRED", 
  "status_at": "2017-07-20", 
  "subjects": [
    "Arts, culture, religion"
  ], 
  "subjects_top_term": "Arts, culture, religion", 
  "summary": {
    "as": "Introduced in House", 
    "date": "2017-07-20T04:00:00Z", 
    "text": "Maya Angelou Congressional Gold Medal Act\n\nThis bill directs the Speaker of the House of Representatives and the President pro tempore of the Senate to arrange for the posthumous presentation of a Congressional Gold Medal in commemoration of Maya Angelou in recognition of her achievements and contributions to American culture and the civil rights movement.\n\nThe bill requires the medal to be given to the Smithsonian Institution.\n\nThe bill expresses the sense of Congress that the Smithsonian Institution make it available for display, particularly at the National Museum of African American History and Culture, or for loan as appropriate, particularly to locations associated with Angelou's life."
  }, 
  "titles": [
    {
      "as": "introduced", 
      "is_for_portion": false, 
      "title": "Maya Angelou Congressional Gold Medal Act", 
      "type": "short"
    }, 
    {
      "as": "introduced", 
      "is_for_portion": false, 
      "title": "Maya Angelou Congressional Gold Medal Act", 
      "type": "short"
    }, 
    {
      "as": "introduced", 
      "is_for_portion": false, 
      "title": "To posthumously award a Congressional gold medal to Maya Angelou in recognition of her achievements and contributions to American culture and the civil rights movement.", 
      "type": "official"
    }, 
    {
      "as": null, 
      "is_for_portion": false, 
      "title": "Maya Angelou Congressional Gold Medal Act", 
      "type": "display"
    }
  ], 
  "updated_at": "2017-09-08T14:17:06Z", 
  "url": "https://www.gpo.gov/fdsys/bulkdata/BILLSTATUS/115/hr/BILLSTATUS-115hr3334.xml"
}