<bill session="115" type="s" number="290" updated="2017-06-19T21:00:26Z">
  <state datetime="2017-02-02">REFERRED</state>
  <status>
    <introduced datetime="2017-02-02"/>
  </status>
  <introduced datetime="2017-02-02"/>
  <titles>
    <title type="short" as="introduced">Helping Our Middle-Class Entrepreneurs Act</title>
    <title type="short" as="introduced">Helping Our Middle-Class Entrepreneurs Act</title>
    <title type="short" as="introduced">HOME Act</title>
    <title type="short" as="introduced">HOME Act</title>
    <title type="official" as="introduced">A bill to amend the Internal Revenue Code of 1986 to provide a standard home office deduction.</title>
    <title type="display">HOME Act</title>
  </titles>
  <sponsor bioguide_id="U000039"/>
  <cosponsors>
    <cosponsor bioguide_id="B001236" joined="2017-02-02"/>
  </cosponsors>
  <actions>
    <action datetime="2017-02-02">
      <text>Introduced in Senate</text>
    </action>
    <action datetime="2017-02-02" state="REFERRED">
      <text>Read twice and referred to the Committee on Finance.</text>
    </action>
  </actions>
  <committees>
    <committee subcommittee="" code="SSFI" name="Senate Finance" activity="Referral"/>
  </committees>
  <relatedbills>
    <bill type="h" session="115" relation="identical" number="836"/>
  </relatedbills>
  <subjects>
    <term name="Taxation"/>
    <term name="Business investment and capital"/>
    <term name="Housing finance and home ownership"/>
    <term name="Income tax deductions"/>
    <term name="Inflation and prices"/>
  </subjects>
  <amendments/>
  <summary date="2017-02-02T05:00:00Z" status="Introduced in Senate">Helping Our Middle-Class Entrepreneurs Act or the HOME Act

 This bill amends the Internal Revenue Code to allow a taxpayer who uses a residence to conduct a trade or business a standard tax deduction equal to the lesser of $1,500 or the taxpayer's gross trade or business income derived from the business use of such residence. The bill provides for an inflation adjustment to the standard deduction amount in calendar years beginning after 2017.</summary>
  <committee-reports/>
</bill>
