{
  "actions": [
    {
      "acted_at": "2017-06-12", 
      "action_code": "Intro-H", 
      "references": [], 
      "text": "Introduced in House", 
      "type": "action"
    }, 
    {
      "acted_at": "2017-06-12", 
      "action_code": "H11100", 
      "committees": [
        "HSED"
      ], 
      "references": [], 
      "status": "REFERRED", 
      "text": "Referred to the House Committee on Education and the Workforce.", 
      "type": "referral"
    }
  ], 
  "amendments": [], 
  "bill_id": "hr2878-115", 
  "bill_type": "hr", 
  "by_request": false, 
  "committee_reports": [], 
  "committees": [
    {
      "activity": [
        "referral"
      ], 
      "committee": "House Education and the Workforce", 
      "committee_id": "HSED"
    }
  ], 
  "congress": "115", 
  "cosponsors": [
    {
      "bioguide_id": "B001292", 
      "district": "8", 
      "name": "Beyer, Donald S., Jr.", 
      "original_cosponsor": true, 
      "sponsored_at": "2017-06-12", 
      "state": "VA", 
      "title": "Rep", 
      "withdrawn_at": null
    }, 
    {
      "bioguide_id": "B000574", 
      "district": "3", 
      "name": "Blumenauer, Earl", 
      "original_cosponsor": true, 
      "sponsored_at": "2017-06-12", 
      "state": "OR", 
      "title": "Rep", 
      "withdrawn_at": null
    }, 
    {
      "bioguide_id": "C001037", 
      "district": "7", 
      "name": "Capuano, Michael E.", 
      "original_cosponsor": true, 
      "sponsored_at": "2017-06-12", 
      "state": "MA", 
      "title": "Rep", 
      "withdrawn_at": null
    }, 
    {
      "bioguide_id": "C001090", 
      "district": "17", 
      "name": "Cartwright, Matt", 
      "original_cosponsor": true, 
      "sponsored_at": "2017-06-12", 
      "state": "PA", 
      "title": "Rep", 
      "withdrawn_at": null
    }, 
    {
      "bioguide_id": "C001101", 
      "district": "5", 
      "name": "Clark, Katherine M.", 
      "original_cosponsor": true, 
      "sponsored_at": "2017-06-12", 
      "state": "MA", 
      "title": "Rep", 
      "withdrawn_at": null
    }, 
    {
      "bioguide_id": "D000399", 
      "district": "35", 
      "name": "Doggett, Lloyd", 
      "original_cosponsor": false, 
      "sponsored_at": "2017-06-20", 
      "state": "TX", 
      "title": "Rep", 
      "withdrawn_at": null
    }, 
    {
      "bioguide_id": "E000288", 
      "district": "5", 
      "name": "Ellison, Keith", 
      "original_cosponsor": false, 
      "sponsored_at": "2017-07-12", 
      "state": "MN", 
      "title": "Rep", 
      "withdrawn_at": null
    }, 
    {
      "bioguide_id": "G000551", 
      "district": "3", 
      "name": "Grijalva, Raul M.", 
      "original_cosponsor": true, 
      "sponsored_at": "2017-06-12", 
      "state": "AZ", 
      "title": "Rep", 
      "withdrawn_at": null
    }, 
    {
      "bioguide_id": "G000535", 
      "district": "4", 
      "name": "Gutierrez, Luis V.", 
      "original_cosponsor": true, 
      "sponsored_at": "2017-06-12", 
      "state": "IL", 
      "title": "Rep", 
      "withdrawn_at": null
    }, 
    {
      "bioguide_id": "H000324", 
      "district": "20", 
      "name": "Hastings, Alcee L.", 
      "original_cosponsor": true, 
      "sponsored_at": "2017-06-12", 
      "state": "FL", 
      "title": "Rep", 
      "withdrawn_at": null
    }, 
    {
      "bioguide_id": "M000312", 
      "district": "2", 
      "name": "McGovern, James P.", 
      "original_cosponsor": true, 
      "sponsored_at": "2017-06-12", 
      "state": "MA", 
      "title": "Rep", 
      "withdrawn_at": null
    }, 
    {
      "bioguide_id": "N000147", 
      "district": null, 
      "name": "Norton, Eleanor Holmes", 
      "original_cosponsor": true, 
      "sponsored_at": "2017-06-12", 
      "state": "DC", 
      "title": "Rep", 
      "withdrawn_at": null
    }, 
    {
      "bioguide_id": "P000607", 
      "district": "2", 
      "name": "Pocan, Mark", 
      "original_cosponsor": true, 
      "sponsored_at": "2017-06-12", 
      "state": "WI", 
      "title": "Rep", 
      "withdrawn_at": null
    }, 
    {
      "bioguide_id": "R000486", 
      "district": "40", 
      "name": "Roybal-Allard, Lucille", 
      "original_cosponsor": true, 
      "sponsored_at": "2017-06-12", 
      "state": "CA", 
      "title": "Rep", 
      "withdrawn_at": null
    }, 
    {
      "bioguide_id": "S001150", 
      "district": "28", 
      "name": "Schiff, Adam B.", 
      "original_cosponsor": true, 
      "sponsored_at": "2017-06-12", 
      "state": "CA", 
      "title": "Rep", 
      "withdrawn_at": null
    }, 
    {
      "bioguide_id": "T000472", 
      "district": "41", 
      "name": "Takano, Mark", 
      "original_cosponsor": true, 
      "sponsored_at": "2017-06-12", 
      "state": "CA", 
      "title": "Rep", 
      "withdrawn_at": null
    }
  ], 
  "enacted_as": null, 
  "history": {
    "active": false, 
    "awaiting_signature": false, 
    "enacted": false, 
    "vetoed": false
  }, 
  "introduced_at": "2017-06-12", 
  "number": "2878", 
  "official_title": "To amend the Fair Labor Standards Act of 1938 to prohibit employment of children in tobacco-related agriculture by deeming such employment as oppressive child labor.", 
  "popular_title": null, 
  "related_bills": [
    {
      "bill_id": "s1341-115", 
      "identified_by": "CRS", 
      "reason": "identical", 
      "type": "bill"
    }
  ], 
  "short_title": "Children Don't Belong on Tobacco Farms Act", 
  "sponsor": {
    "bioguide_id": "C001084", 
    "district": "1", 
    "name": "Cicilline, David N.", 
    "state": "RI", 
    "title": "Rep", 
    "type": "person"
  }, 
  "status": "REFERRED", 
  "status_at": "2017-06-12", 
  "subjects": [
    "Labor and employment"
  ], 
  "subjects_top_term": "Labor and employment", 
  "summary": null, 
  "titles": [
    {
      "as": "introduced", 
      "is_for_portion": false, 
      "title": "Children Don't Belong on Tobacco Farms Act", 
      "type": "short"
    }, 
    {
      "as": "introduced", 
      "is_for_portion": false, 
      "title": "Children Don\u2019t Belong on Tobacco Farms Act", 
      "type": "short"
    }, 
    {
      "as": "introduced", 
      "is_for_portion": false, 
      "title": "To amend the Fair Labor Standards Act of 1938 to prohibit employment of children in tobacco-related agriculture by deeming such employment as oppressive child labor.", 
      "type": "official"
    }, 
    {
      "as": null, 
      "is_for_portion": false, 
      "title": "Children Don't Belong on Tobacco Farms Act", 
      "type": "display"
    }
  ], 
  "updated_at": "2017-07-13T07:16:57Z", 
  "url": "https://www.gpo.gov/fdsys/bulkdata/BILLSTATUS/115/hr/BILLSTATUS-115hr2878.xml"
}